deezepy/__init__.py
deezepy/client.py
deezepy/errors.py
deezepy/types.py
deezepy-0.2.1.dist-info/LICENSE
deezepy-0.2.1.dist-info/METADATA
deezepy-0.2.1.dist-info/WHEEL
deezepy-0.2.1.dist-info/top_level.txt
deezepy-0.2.1.dist-info/RECORD
