Metadata-Version: 2.1
Name: deezepy
Version: 0.2.1
Summary: Deezer wrapper written in Python
Home-page: https://github.com/CyanBook/deezepy
Author: CyanBook
Author-email: lorenzo.delmonte05@gmail.com
License: UNKNOWN
Platform: UNKNOWN
Classifier: Programming Language :: Python :: 3
Requires-Python: >=3.6
Requires-Dist: requests
